yudkow_models/Blip2.py
yudkow_models/ChatGPT.py
yudkow_models/MiniLM.py
yudkow_models/T5.py
yudkow_models/Translator.py
yudkow_models/__init__.py
yudkow_models-0.2.dist-info/METADATA
yudkow_models-0.2.dist-info/WHEEL
yudkow_models-0.2.dist-info/top_level.txt
yudkow_models-0.2.dist-info/RECORD
