Metadata-Version: 2.2
Name: yudkow-models
Version: 0.2
Summary: My package with models
Author: BlTT
Author-email: bltt6956@gmail.com
Classifier: Programming Language :: Python :: 3
Classifier: License :: OSI Approved :: MIT License
Classifier: Operating System :: OS Independent
Requires-Python: >=3.6
Dynamic: author
Dynamic: author-email
Dynamic: classifier
Dynamic: requires-python
Dynamic: summary
